datarray/LICENSE
datarray/__init__.py
datarray/datarray.py
datarray/print_grid.py
datarray/version.py
datarray/testing/__init__.py
datarray/testing/testlib.py
datarray/testing/utils.py
datarray/tests/__init__.py
datarray/tests/test_bugfixes.py
datarray/tests/test_data_array.py
datarray/tests/test_print.py
datarray-0.1.0.dist-info/DESCRIPTION.rst
datarray-0.1.0.dist-info/METADATA
datarray-0.1.0.dist-info/RECORD
datarray-0.1.0.dist-info/WHEEL
datarray-0.1.0.dist-info/metadata.json
datarray-0.1.0.dist-info/top_level.txt
