Metadata-Version: 2.0
Name: datarray
Version: 0.1.0
Summary: NumPy arrays with named axes and named indices.
Home-page: http://github.com/bids/datarray
Author: Numpy Developers
Author-email: numpy-discussion@scipy.org
License: Simplified BSD
Download-URL: http://github.com/bids/datarray/archives/master
Platform: OS Independent
Classifier: Development Status :: 3 - Alpha
Classifier: Environment :: Console
Classifier: Intended Audience :: Science/Research
Classifier: License :: OSI Approved :: BSD License
Classifier: Operating System :: OS Independent
Classifier: Programming Language :: Python
Classifier: Topic :: Scientific/Engineering
Requires: numpy (>=1.7)
Requires-Dist: numpy (>=1.7)
